dillagent/__init__.py
dillagent/agents/__init__.py
dillagent/agents/agents/__init__.py
dillagent/agents/agents/BaseAgent.py
dillagent/agents/agents/StarterAgent.py
dillagent/agents/executors/__init__.py
dillagent/agents/executors/BaseAgentExecutor.py
dillagent/dependencies/__init__.py
dillagent/dependencies/parsers/__init__.py
dillagent/dependencies/parsers/intermediate/__init__.py
dillagent/dependencies/parsers/intermediate/BaseIntermediateParser.py
dillagent/dependencies/parsers/intermediate/JsonParser.py
dillagent/dependencies/prompts/__init__.py
dillagent/dependencies/prompts/BaseSysPrompt.py
dillagent/dependencies/prompts/MultiAgentSupervisorSysPrompt.py
dillagent/dependencies/prompts/MultiInputToolsSysPrompt.py
dillagent/dependencies/prompts/StructuredPrompt.py
dillagent/llm/__init__.py
dillagent/llm/AnthropicLLM.py
dillagent/llm/CustomLLM.py
dillagent/llm/LLM.py
dillagent/llm/LLMConfig.py
dillagent/llm/OpenAILLM.py
dillagent/models/__init__.py
dillagent/models/DescribedModel.py
dillagent/tools/__init__.py
dillagent/tools/Tool.py
dillagent/workflows/__init__.py
dillagent/workflows/BaseWorkflowExecutor.py
dillagent/workflows/graphs/__init__.py
dillagent/workflows/graphs/clusters/__init__.py
dillagent/workflows/graphs/clusters/BaseAgentCluster.py
dillagent/workflows/graphs/executors/__init__.py
dillagent/workflows/graphs/executors/BaseAgentGraphExecutor.py
dillagent/workflows/graphs/executors/PlannerAgentGraphExecutor.py
dillagent/workflows/graphs/graphs/__init__.py
dillagent/workflows/graphs/graphs/BaseAgentGraph.py
dillagent-1.0.8.dist-info/LICENSE
dillagent-1.0.8.dist-info/METADATA
dillagent-1.0.8.dist-info/WHEEL
dillagent-1.0.8.dist-info/RECORD
